django_spinproject/cli.py
django_spinproject/constants.py
django_spinproject/bin/spinproject.py
django_spinproject/generic/__init__.py
django_spinproject/generic/dicts_merging.py
django_spinproject/generic/directory_cleaning.py
django_spinproject/generic/exit.py
django_spinproject/generic/extended_jinja_environment.py
django_spinproject/generic/file_upgrade.py
django_spinproject/generic/hash.py
django_spinproject/generic/package.py
django_spinproject/generic/serialization.py
django_spinproject/generic/version_registry.py
django_spinproject/modules/__init__.py
django_spinproject/modules/_base.py
django_spinproject/modules/_mixins.py
django_spinproject/modules/docker_scripts.py
django_spinproject/modules/dockerfile.py
django_spinproject/modules/dockerignore.py
django_spinproject/modules/gitignore.py
django_spinproject/modules/gitlab_ci.py
django_spinproject/modules/login_template.py
django_spinproject/modules/pg_readonly.py
django_spinproject/modules/pytest.py
django_spinproject/modules/settings.py
django_spinproject/modules/srta.py
django_spinproject/modules/docker_scripts_data/__init__.py
django_spinproject/modules/docker_scripts_data/v1.py
django_spinproject/modules/docker_scripts_data/v2.py
django_spinproject/modules/docker_scripts_data/v3.py
django_spinproject/modules/dockerfile_data/__init__.py
django_spinproject/modules/dockerfile_data/v1.py
django_spinproject/modules/dockerfile_data/v2.py
django_spinproject/modules/dockerfile_data/v3.py
django_spinproject/modules/dockerfile_data/v4.py
django_spinproject/modules/dockerfile_data/v5.py
django_spinproject/modules/dockerignore_data/__init__.py
django_spinproject/modules/dockerignore_data/v1.py
django_spinproject/modules/dockerignore_data/v2.py
django_spinproject/modules/dockerignore_data/v3.py
django_spinproject/modules/dockerignore_data/v4.py
django_spinproject/modules/gitignore_data/__init__.py
django_spinproject/modules/gitignore_data/v1.py
django_spinproject/modules/gitignore_data/v2.py
django_spinproject-3.0.0.dist-info/METADATA
django_spinproject-3.0.0.dist-info/WHEEL
django_spinproject-3.0.0.dist-info/entry_points.txt
django_spinproject-3.0.0.dist-info/licenses/LICENSE
django_spinproject-3.0.0.dist-info/RECORD
