Metadata-Version: 2.4
Name: django-spinproject
Version: 3.0.0
Summary: Opinionated version of `startproject` with some popular third-party packages. Starter pack includes: whitenoise, django-environ, logging, GitHub Scripts to Rule Them All, basic Dockerfile and Makefile.
Project-URL: homepage, https://github.com/m1kc/django-spinproject
Project-URL: repository, https://github.com/m1kc/django-spinproject.git
Project-URL: documentation, https://github.com/m1kc/django-spinproject
Author-email: "m1kc (Max Musatov)" <m1kc@yandex.ru>
License-Expression: MIT
License-File: LICENSE
Keywords: SRTA,django,django-admin,django-environ,startproject,template,whitenoise
Classifier: Operating System :: OS Independent
Requires-Python: >=3.7
Requires-Dist: jinja2>=3.1.2
